{"J+vsPASXkvXXvBU/w+NaPw==":"img-1589-2000x1500.jpg","MRkQ+t5KxtG4q6TAuc3Flw==":"img-1590-2000x1500.jpg","RX/oS6DEOVnRMwn4d2U5Aw==":"img-2493-2000x2662.jpg","fNryRyG5gAgEpTyYdFZPWQ==":"img-2494-2000x2662.jpg","wZdJj3QOYjr8JYKYqG9v4Q==":"img-8835-2000x2667.jpg","k3MNIdYqC57IhSG/lTniOA==":"img-3952-2000x1500.jpg","apq+FuI/5osHZSRgsWxLdA==":"img-3953-2000x1500.jpg","EH150Uw/gNEmyHflV2m4lg==":"img-3954-2000x1500.jpg","ZiiYbBePi0DjtuLxGYslmA==":"img-1918-2000x1500.jpg","4BS1RhHgsbx/sPV/DzuLbw==":"img-1919-2000x1500.jpg","LaTcisxAzvq9KvkyyLnLrg==":"img-8834-2000x2667.jpg","S9t3lJDSmkOrQbuxhZVU6w==":"img-8836-2000x2667.jpg","oo2UgYv12Gdx/b+FnTWHWA==":"img-3955-2000x1500.jpg"}